MANIFEST.in
README.rst
setup.cfg
setup.py
pagina46/README.md
pagina46/__init__.py
pagina46/admin.py
pagina46/apps.py
pagina46/context_processors.py
pagina46/models.py
pagina46/tests.py
pagina46/utils.py
pagina46/views.py
pagina46.egg-info/PKG-INFO
pagina46.egg-info/SOURCES.txt
pagina46.egg-info/dependency_links.txt
pagina46.egg-info/top_level.txt
pagina46/__pycache__/__init__.cpython-37.pyc
pagina46/__pycache__/admin.cpython-37.pyc
pagina46/__pycache__/context_processors.cpython-37.pyc
pagina46/__pycache__/models.cpython-37.pyc
pagina46/__pycache__/utils.cpython-37.pyc
pagina46/__pycache__/views.cpython-37.pyc
pagina46/migrations/__init__.py
pagina46/migrations/__pycache__/__init__.cpython-37.pyc
pagina46/static/css/p46style.css
pagina46/static/images/logobianco.svg
pagina46/templates/pagina46/base.html
pagina46/templates/pagina46/footer.html
pagina46/templatetags/__init__.py
pagina46/templatetags/git.py
pagina46/templatetags/p46static.py
pagina46/templatetags/__pycache__/__init__.cpython-37.pyc
pagina46/templatetags/__pycache__/git.cpython-37.pyc
pagina46/templatetags/__pycache__/p46static.cpython-37.pyc
pagina46prg/__init__.py
pagina46prg/asgi.py
pagina46prg/settings.py
pagina46prg/urls.py
pagina46prg/wsgi.py