Metadata-Version: 1.1
Name: pagina46
Version: 1.0.3
Summary: Django pagina46.
Home-page: UNKNOWN
Author: Pagina46
Author-email: info@pagina46.it
License: UNKNOWN
Platform: UNKNOWN
Classifier: Environment :: Web Environment
Classifier: Framework :: Django
Classifier: Intended Audience :: Developers
Classifier: Operating System :: OS Independent
Classifier: Programming Language :: Python
Classifier: Programming Language :: Python :: 3
Classifier: Topic :: Internet :: WWW/HTTP
